choreo/__init__.py
choreo/py.typed
choreo/test/choreolib_test.py
choreo/test/sample_flipping_test.py
choreo/trajectory/__init__.py
choreo/util/__init__.py
choreo/util/field_dimensions.py
choreo/util/traj_schema_version.py
sleipnirgroup_choreolib-2025.0.3.dist-info/METADATA
sleipnirgroup_choreolib-2025.0.3.dist-info/WHEEL
sleipnirgroup_choreolib-2025.0.3.dist-info/top_level.txt
sleipnirgroup_choreolib-2025.0.3.dist-info/RECORD
