Metadata-Version: 2.2
Name: sleipnirgroup-choreolib
Version: 2025.0.3
Summary: Robot-side library for parsing and following Choreo paths.
Author: Choreo Development Team
License: BSD-3-Clause
Project-URL: Documentation, https://choreo.autos/
Requires-Python: >=3.9
Requires-Dist: wpilib
